vetoes/__init__.py
vetoes/config.py
vetoes/service.py
vetoes-0.4.0.dist-info/top_level.txt
vetoes-0.4.0.dist-info/METADATA
vetoes-0.4.0.dist-info/DESCRIPTION.rst
vetoes-0.4.0.dist-info/metadata.json
vetoes-0.4.0.dist-info/WHEEL
vetoes-0.4.0.dist-info/RECORD
