Metadata-Version: 2.0
Name: vetoes
Version: 0.4.0
Summary: Rejected companion library
Home-page: https://github.com/dave-shawley/vetoes
Author: Dave Shawley
Author-email: daveshawley+python@gmail.com
License: UNKNOWN
Platform: any
Classifier: Intended Audience :: Developers
Classifier: License :: OSI Approved :: BSD License
Classifier: Operating System :: OS Independent
Classifier: Programming Language :: Python
Classifier: Programming Language :: Python :: 2
Classifier: Programming Language :: Python :: 3
Classifier: Development Status :: 4 - Beta
Requires-Dist: rejected
